dune.gdt-2022.5.3-py3.9-nspkg.pth
dune/gdt/_version.py
dune/gdt/_interpolations_boundary.cpython-39-x86_64-linux-gnu.so
dune/gdt/basic.py
dune/gdt/_local_bilinear_forms_element_interface.cpython-39-x86_64-linux-gnu.so
dune/gdt/__init__.py
dune/gdt/_local_functionals_restricted_intersection_integrals.cpython-39-x86_64-linux-gnu.so
dune/gdt/_functionals_interfaces_istl.cpython-39-x86_64-linux-gnu.so
dune/gdt/_tools_sparsity_pattern.cpython-39-x86_64-linux-gnu.so
dune/gdt/_spaces_h1_continuous_lagrange.cpython-39-x86_64-linux-gnu.so
dune/gdt/_operators_interfaces_istl_2d.cpython-39-x86_64-linux-gnu.so
dune/gdt/_discretefunction_discretefunction.cpython-39-x86_64-linux-gnu.so
dune/gdt/_spaces_l2_finite_volume.cpython-39-x86_64-linux-gnu.so
dune/gdt/_local_bilinear_forms_coupling_intersection_interface.cpython-39-x86_64-linux-gnu.so
dune/gdt/_local_bilinear_forms_restricted_coupling_intersection_integrals.cpython-39-x86_64-linux-gnu.so
dune/gdt/_discretefunction_bochner.cpython-39-x86_64-linux-gnu.so
dune/gdt/_spaces_hdiv_raviart_thomas.cpython-39-x86_64-linux-gnu.so
dune/gdt/_spaces_interface.cpython-39-x86_64-linux-gnu.so
dune/gdt/_tools_adaptation_helper.cpython-39-x86_64-linux-gnu.so
dune/gdt/_interpolations_default.cpython-39-x86_64-linux-gnu.so
dune/gdt/_local_bilinear_forms_intersection_integrals.cpython-39-x86_64-linux-gnu.so
dune/gdt/_operators_operator.cpython-39-x86_64-linux-gnu.so
dune/gdt/_local_bilinear_forms_restricted_intersection_integrals.cpython-39-x86_64-linux-gnu.so
dune/gdt/_local_functionals_element_integrals.cpython-39-x86_64-linux-gnu.so
dune/gdt/_local_integrands_linear_advection.cpython-39-x86_64-linux-gnu.so
dune/gdt/_tools_dirichlet_constraints.cpython-39-x86_64-linux-gnu.so
dune/gdt/_local_integrands_binary_intersection_interface.cpython-39-x86_64-linux-gnu.so
dune/gdt/_local_bilinear_forms_intersection_interface.cpython-39-x86_64-linux-gnu.so
dune.gdt-2022.5.3.dist-info/LICENSE.txt
dune.gdt-2022.5.3.dist-info/namespace_packages.txt
dune.gdt-2022.5.3.dist-info/RECORD
dune.gdt-2022.5.3.dist-info/METADATA
dune.gdt-2022.5.3.dist-info/top_level.txt
dune.gdt-2022.5.3.dist-info/WHEEL
