Metadata-Version: 2.1
Name: dune.gdt
Version: 2022.5.3
Summary: Python for Dune-Gdt
Home-page: https://zivgitlab.uni-muenster.de/ag-ohlberger/dune-community/dune-gdt
Author: The dune-gdt devs
Author-email: felix.schindler@wwu.de
License-File: LICENSE.txt
Requires-Dist: dune.xt (==2022.5.3)
Provides-Extra: all
Requires-Dist: dune-xt[visualisation] (==2022.5.3) ; extra == 'all'
Requires-Dist: dune-xt[infrastructure] (==2022.5.3) ; extra == 'all'
Requires-Dist: dune-xt[parallel] (==2022.5.3) ; extra == 'all'
Provides-Extra: infrastructure
Requires-Dist: dune-xt[infrastructure] (==2022.5.3) ; extra == 'infrastructure'
Provides-Extra: parallel
Requires-Dist: dune-xt[parallel] (==2022.5.3) ; extra == 'parallel'
Provides-Extra: visualisation
Requires-Dist: dune-xt[visualisation] (==2022.5.3) ; extra == 'visualisation'
